xsc/__init__.py
xsc/_modidx.py
xsc/attr.py
xsc/data.py
xsc/plot.py
xsc/sens.py
xsc/test.py
xsc/util.py
xsc-0.0.12.dist-info/LICENSE
xsc-0.0.12.dist-info/METADATA
xsc-0.0.12.dist-info/WHEEL
xsc-0.0.12.dist-info/entry_points.txt
xsc-0.0.12.dist-info/top_level.txt
xsc-0.0.12.dist-info/RECORD
