Metadata-Version: 2.1
Name: xsc
Version: 0.0.12
Summary: xsc
Home-page: https://github.com/dsm-72/xsc
Author: dsm-72
Author-email: sumner.magruder@yale.edu
License: Apache Software License 2.0
Keywords: xsc extra extras single cell sc scanpy anndata RNA-seq seq
Classifier: Development Status :: 4 - Beta
Classifier: Intended Audience :: Developers
Classifier: Natural Language :: English
Classifier: Programming Language :: Python :: 3.11
Classifier: License :: OSI Approved :: Apache Software License
Requires-Python: >=3.11
License-File: LICENSE
Requires-Dist: nchr
Requires-Dist: nlit
Requires-Dist: astr
Requires-Dist: uscr
Requires-Dist: pdec
Requires-Dist: itry
Requires-Dist: matr
Requires-Dist: atyp
Requires-Dist: psrc
Requires-Dist: chck
Requires-Dist: asto
Requires-Dist: calr
Requires-Dist: hasr
Requires-Dist: fpos
Requires-Dist: akey
Requires-Dist: mstar
Requires-Dist: numpy >=1.22
Provides-Extra: dev
Requires-Dist: pandas ; extra == 'dev'
Requires-Dist: numpy >=1.22 ; extra == 'dev'
Requires-Dist: scipy ; extra == 'dev'
Requires-Dist: anndata ; extra == 'dev'
Requires-Dist: scanpy ; extra == 'dev'
Requires-Dist: scrublet ; extra == 'dev'
Requires-Dist: scprep ; extra == 'dev'
Requires-Dist: phate ; extra == 'dev'
Requires-Dist: magic-impute ; extra == 'dev'
Requires-Dist: graphtools ; extra == 'dev'
Requires-Dist: matplotlib ; extra == 'dev'
Requires-Dist: seaborn ; extra == 'dev'
